{"trials":[{"item":"170","conditions":"ueb","read_time":[4812],"image_error":false,"slider_value":100},{"item":"171","conditions":"ueb","read_time":[4629],"image_error":false,"slider_value":100},{"item":"169","conditions":"ueb","read_time":[4503],"image_error":false,"slider_value":-1},{"item":"105","conditions":"grosse_unscharf","read_time":[4876],"image_error":false,"slider_value":0},{"item":"51","conditions":"grosse_scharf","read_time":[4605],"image_error":false,"slider_value":0},{"item":"147","conditions":"farbe_scharf","read_time":[7426],"image_error":false,"slider_value":0},{"item":"150","conditions":"farbe_scharf","read_time":[6229],"image_error":false,"slider_value":100},{"item":"25","conditions":"grosse_scharf","read_time":[5043],"image_error":false,"slider_value":0},{"item":"67","conditions":"farbe_unscharf","read_time":[8348],"image_error":false,"slider_value":-1},{"item":"115","conditions":"grosse_unscharf","read_time":[4770],"image_error":false,"slider_value":0},{"item":"35","conditions":"grosse_scharf","read_time":[6187],"image_error":false,"slider_value":100},{"item":"112","conditions":"grosse_unscharf","read_time":[4729],"image_error":false,"slider_value":0},{"item":"1","conditions":"dap","read_time":[4726],"image_error":false,"slider_value":100},{"item":"16","conditions":"dap","read_time":[6204],"image_error":false,"slider_value":0},{"item":"57","conditions":"grosse_scharf","read_time":[4841],"image_error":false,"slider_value":0},{"item":"102","conditions":"grosse_unscharf","read_time":[4289],"image_error":false,"slider_value":100},{"item":"99","conditions":"grosse_unscharf","read_time":[10687],"image_error":false,"slider_value":100},{"item":"32","conditions":"grosse_scharf","read_time":[5361],"image_error":false,"slider_value":100},{"item":"4","conditions":"dap","read_time":[4115],"image_error":false,"slider_value":100},{"item":"21","conditions":"dap","read_time":[5731],"image_error":false,"slider_value":100},{"item":"15","conditions":"dap","read_time":[4144],"image_error":false,"slider_value":0},{"item":"89","conditions":"farbe_unscharf","read_time":[17056],"image_error":false,"slider_value":100},{"item":"20","conditions":"dap","read_time":[3602],"image_error":false,"slider_value":0},{"item":"19","conditions":"dap","read_time":[9536],"image_error":false,"slider_value":0},{"item":"38","conditions":"grosse_scharf","read_time":[6188],"image_error":false,"slider_value":0},{"item":"48","conditions":"grosse_scharf","read_time":[7366],"image_error":false,"slider_value":0},{"item":"17","conditions":"dap","read_time":[16175],"image_error":false,"slider_value":57},{"item":"128","conditions":"grosse_unscharf","read_time":[6478],"image_error":false,"slider_value":100},{"item":"9","conditions":"dap","read_time":[3406],"image_error":false,"slider_value":0},{"item":"160","conditions":"farbe_scharf","read_time":[8258],"image_error":false,"slider_value":100},{"item":"70","conditions":"farbe_unscharf","read_time":[6419],"image_error":false,"slider_value":0},{"item":"14","conditions":"dap","read_time":[4086],"image_error":false,"slider_value":100},{"item":"118","conditions":"grosse_unscharf","read_time":[3906],"image_error":false,"slider_value":100},{"item":"137","conditions":"farbe_scharf","read_time":[5979],"image_error":false,"slider_value":-1},{"item":"8","conditions":"dap","read_time":[7932],"image_error":false,"slider_value":0},{"item":"131","conditions":"grosse_unscharf","read_time":[5170],"image_error":false,"slider_value":100},{"item":"134","conditions":"farbe_scharf","read_time":[15628],"image_error":false,"slider_value":0},{"item":"86","conditions":"farbe_unscharf","read_time":[9675],"image_error":false,"slider_value":100},{"item":"22","conditions":"dap","read_time":[4797],"image_error":false,"slider_value":0},{"item":"2","conditions":"dap","read_time":[6395],"image_error":false,"slider_value":100},{"item":"64","conditions":"farbe_unscharf","read_time":[11099],"image_error":false,"slider_value":100},{"item":"73","conditions":"farbe_unscharf","read_time":[10928],"image_error":false,"slider_value":-1},{"item":"166","conditions":"farbe_scharf","read_time":[12635],"image_error":false,"slider_value":0},{"item":"23","conditions":"dap","read_time":[6651],"image_error":false,"slider_value":0},{"item":"24","conditions":"dap","read_time":[4265],"image_error":false,"slider_value":100},{"item":"5","conditions":"dap","read_time":[4739],"image_error":false,"slider_value":100},{"item":"6","conditions":"dap","read_time":[3564],"image_error":false,"slider_value":0},{"item":"144","conditions":"farbe_scharf","read_time":[15169],"image_error":false,"slider_value":100},{"item":"10","conditions":"dap","read_time":[3578],"image_error":false,"slider_value":100},{"item":"11","conditions":"dap","read_time":[6741],"image_error":false,"slider_value":100},{"item":"83","conditions":"farbe_unscharf","read_time":[13149],"image_error":false,"slider_value":55},{"item":"12","conditions":"dap","read_time":[3529],"image_error":false,"slider_value":0},{"item":"121","conditions":"grosse_unscharf","read_time":[5867],"image_error":false,"slider_value":100},{"item":"54","conditions":"grosse_scharf","read_time":[5614],"image_error":false,"slider_value":100},{"item":"80","conditions":"farbe_unscharf","read_time":[10112],"image_error":false,"slider_value":100},{"item":"153","conditions":"farbe_scharf","read_time":[5043],"image_error":false,"slider_value":0},{"item":"96","conditions":"farbe_unscharf","read_time":[8685],"image_error":false,"slider_value":-1},{"item":"7","conditions":"dap","read_time":[4048],"image_error":false,"slider_value":100},{"item":"41","conditions":"grosse_scharf","read_time":[11687],"image_error":false,"slider_value":0},{"item":"163","conditions":"farbe_scharf","read_time":[9885],"image_error":false,"slider_value":0},{"item":"18","conditions":"dap","read_time":[6068],"image_error":false,"slider_value":0},{"item":"13","conditions":"dap","read_time":[3270],"image_error":false,"slider_value":100},{"item":"3","conditions":"dap","read_time":[4515],"image_error":false,"slider_value":0}],"id":"60f15f2ae872b0","catch_trials":[],"block_boundaries":[14,30,44],"system":{"Browser":"Safari","OS":"Mac","screenH":900,"screenW":1440},"condition":"L","subject_information":{"language":"Deutsch","asses":"Yes","age":"20","gender":"Male","comments":"","fluent":"Yes"},"time_in_minutes":8.453483333333333,"missed_break_one":false,"missed_break_two":false,"missed_break_three":false}