{"trials":[{"item":"39","conditions":"ubrcf","read_time":[32490],"image_error":false,"slider_value":50,"leftright_trial":"1right","list":"7"},{"item":"39","conditions":"uzrdf","read_time":[15047],"image_error":false,"slider_value":50,"leftright_trial":"1left","list":"7"},{"item":"39","conditions":"uerdc","read_time":[16313],"image_error":false,"slider_value":50,"leftright_trial":"1left","list":"7"},{"item":"33","conditions":"fbrcf","read_time":[15104],"image_error":false,"slider_value":4,"leftright_trial":"1left","list":"1"},{"item":"10","conditions":"zrcf","read_time":[12332],"image_error":false,"slider_value":50,"leftright_trial":"1right","list":"1"},{"item":"17","conditions":"erdf","read_time":[11251],"image_error":false,"slider_value":50,"leftright_trial":"1right","list":"1"},{"item":"37","conditions":"fzrdc","read_time":[6799],"image_error":false,"slider_value":97,"leftright_trial":"1left","list":"1"},{"item":"35","conditions":"fbrcf","read_time":[23790],"image_error":false,"slider_value":76,"leftright_trial":"1left","list":"1"},{"item":"3","conditions":"zrdf","read_time":[5408],"image_error":false,"slider_value":50,"leftright_trial":"1right","list":"1"},{"item":"12","conditions":"erdc","read_time":[17308],"image_error":false,"slider_value":50,"leftright_trial":"1left","list":"1"},{"item":"32","conditions":"fzrdf","read_time":[10375],"image_error":false,"slider_value":19,"leftright_trial":"1left","list":"1"},{"item":"13","conditions":"zrcf","read_time":[10041],"image_error":false,"slider_value":50,"leftright_trial":"1right","list":"1"},{"item":"37","conditions":"ferdf","read_time":[9090],"image_error":false,"slider_value":14,"leftright_trial":"1left","list":"1"},{"item":"5","conditions":"zrcf","read_time":[8007],"image_error":false,"slider_value":50,"leftright_trial":"1right","list":"1"},{"item":"4","conditions":"brdc","read_time":[7281],"image_error":false,"slider_value":50,"leftright_trial":"1right","list":"1"},{"item":"38","conditions":"fzrdf","read_time":[20117],"image_error":false,"slider_value":3,"leftright_trial":"1right","list":"1"},{"item":"31","conditions":"fzrdf","read_time":[14629],"image_error":false,"slider_value":11,"leftright_trial":"1right","list":"1"},{"item":"7","conditions":"brdc","read_time":[7068],"image_error":false,"slider_value":50,"leftright_trial":"1left","list":"1"},{"item":"38","conditions":"ferdc","read_time":[5763],"image_error":false,"slider_value":4,"leftright_trial":"1left","list":"1"},{"item":"23","conditions":"erdc","read_time":[6770],"image_error":false,"slider_value":50,"leftright_trial":"1left","list":"1"},{"item":"5","conditions":"ercf","read_time":[6370],"image_error":false,"slider_value":50,"leftright_trial":"1left","list":"1"},{"item":"33","conditions":"fbrdc","read_time":[10364],"image_error":false,"slider_value":1,"leftright_trial":"1left","list":"1"},{"item":"17","conditions":"brdf","read_time":[5694],"image_error":false,"slider_value":50,"leftright_trial":"1right","list":"1"},{"item":"28","conditions":"fbrdc","read_time":[11438],"image_error":false,"slider_value":2,"leftright_trial":"1left","list":"1"},{"item":"37","conditions":"fzrdf","read_time":[8279],"image_error":false,"slider_value":97,"leftright_trial":"1left","list":"1"},{"item":"36","conditions":"ferdf","read_time":[6961],"image_error":false,"slider_value":97,"leftright_trial":"1right","list":"1"},{"item":"36","conditions":"fbrdf","read_time":[13459],"image_error":false,"slider_value":20,"leftright_trial":"1right","list":"1"},{"item":"20","conditions":"erdc","read_time":[5375],"image_error":false,"slider_value":50,"leftright_trial":"1right","list":"1"},{"item":"32","conditions":"fbrcf","read_time":[12167],"image_error":false,"slider_value":98,"leftright_trial":"1right","list":"1"},{"item":"37","conditions":"fbrdf","read_time":[18397],"image_error":false,"slider_value":63,"leftright_trial":"1left","list":"1"},{"item":"19","conditions":"zrdf","read_time":[4352],"image_error":false,"slider_value":55,"leftright_trial":"1right","list":"1"},{"item":"27","conditions":"zrcf","read_time":[6846],"image_error":false,"slider_value":55,"leftright_trial":"1right","list":"1"},{"item":"19","conditions":"erdf","read_time":[6131],"image_error":false,"slider_value":55,"leftright_trial":"1left","list":"1"},{"item":"38","conditions":"fbrcf","read_time":[12151],"image_error":false,"slider_value":39,"leftright_trial":"1right","list":"1"},{"item":"26","conditions":"zrdc","read_time":[6525],"image_error":false,"slider_value":50,"leftright_trial":"1left","list":"1"},{"item":"19","conditions":"brdf","read_time":[5808],"image_error":false,"slider_value":50,"leftright_trial":"1left","list":"1"},{"item":"22","conditions":"erdf","read_time":[13024],"image_error":false,"slider_value":50,"leftright_trial":"1right","list":"1"},{"item":"30","conditions":"ferdc","read_time":[8419],"image_error":false,"slider_value":4,"leftright_trial":"1left","list":"1"},{"item":"2","conditions":"ercf","read_time":[10226],"image_error":false,"slider_value":50,"leftright_trial":"1left","list":"1"},{"item":"37","conditions":"ferdc","read_time":[7124,13002],"image_error":false,"slider_value":98,"leftright_trial":"1right","list":"1"},{"item":"37","conditions":"fzrcf","read_time":[7381],"image_error":false,"slider_value":74,"leftright_trial":"1left","list":"1"},{"item":"26","conditions":"brdc","read_time":[5586],"image_error":false,"slider_value":50,"leftright_trial":"1right","list":"1"},{"item":"1","conditions":"erdc","read_time":[4529],"image_error":false,"slider_value":50,"leftright_trial":"1right","list":"1"},{"item":"6","conditions":"zrdf","read_time":[5735],"image_error":false,"slider_value":50,"leftright_trial":"1right","list":"1"},{"item":"36","conditions":"fzrdf","read_time":[7308],"image_error":false,"slider_value":2,"leftright_trial":"1right","list":"1"},{"item":"9","conditions":"zrdf","read_time":[8550],"image_error":false,"slider_value":50,"leftright_trial":"1left","list":"1"},{"item":"6","conditions":"brdf","read_time":[7036],"image_error":false,"slider_value":50,"leftright_trial":"1right","list":"1"},{"item":"34","conditions":"ferdf","read_time":[12480],"image_error":false,"slider_value":100,"leftright_trial":"1right","list":"1"},{"item":"34","conditions":"fbrdf","read_time":[5940],"image_error":false,"slider_value":32,"leftright_trial":"1left","list":"1"},{"item":"2","conditions":"zrcf","read_time":[10469],"image_error":false,"slider_value":50,"leftright_trial":"1left","list":"1"},{"item":"5","conditions":"brcf","read_time":[6084],"image_error":false,"slider_value":50,"leftright_trial":"1left","list":"1"},{"item":"34","conditions":"fzrdc","read_time":[4835],"image_error":false,"slider_value":100,"leftright_trial":"1left","list":"1"},{"item":"20","conditions":"zrdc","read_time":[3971],"image_error":false,"slider_value":50,"leftright_trial":"1right","list":"1"},{"item":"30","conditions":"fzrdc","read_time":[11918],"image_error":false,"slider_value":26,"leftright_trial":"1right","list":"1"},{"item":"25","conditions":"brdf","read_time":[6282],"image_error":false,"slider_value":50,"leftright_trial":"1right","list":"1"},{"item":"21","conditions":"ercf","read_time":[4660],"image_error":false,"slider_value":50,"leftright_trial":"1right","list":"1"},{"item":"7","conditions":"erdc","read_time":[7651],"image_error":false,"slider_value":50,"leftright_trial":"1left","list":"1"},{"item":"28","conditions":"fbrcf","read_time":[10653],"image_error":false,"slider_value":3,"leftright_trial":"1left","list":"1"},{"item":"30","conditions":"fercf","read_time":[7406],"image_error":false,"slider_value":17,"leftright_trial":"1left","list":"1"},{"item":"10","conditions":"brcf","read_time":[9856],"image_error":false,"slider_value":50,"leftright_trial":"1left","list":"1"},{"item":"36","conditions":"fzrcf","read_time":[16388],"image_error":false,"slider_value":0,"leftright_trial":"1right","list":"1"},{"item":"34","conditions":"fbrcf","read_time":[18830],"image_error":false,"slider_value":51,"leftright_trial":"1right","list":"1"},{"item":"22","conditions":"brdf","read_time":[8842],"image_error":false,"slider_value":80,"leftright_trial":"1right","list":"1"},{"item":"37","conditions":"fbrdc","read_time":[10682],"image_error":false,"slider_value":30,"leftright_trial":"1right","list":"1"},{"item":"25","conditions":"zrdf","read_time":[8384],"image_error":false,"slider_value":50,"leftright_trial":"1right","list":"1"},{"item":"12","conditions":"zrdc","read_time":[6046],"image_error":false,"slider_value":51,"leftright_trial":"1left","list":"1"},{"item":"2","conditions":"brcf","read_time":[7913],"image_error":false,"slider_value":50,"leftright_trial":"1right","list":"1"},{"item":"38","conditions":"fbrdc","read_time":[7386],"image_error":false,"slider_value":64,"leftright_trial":"1left","list":"1"},{"item":"15","conditions":"erdc","read_time":[8293],"image_error":false,"slider_value":50,"leftright_trial":"1left","list":"1"},{"item":"38","conditions":"fbrdf","read_time":[7359],"image_error":false,"slider_value":67,"leftright_trial":"1left","list":"1"},{"item":"28","conditions":"fbrdf","read_time":[11193],"image_error":false,"slider_value":0,"leftright_trial":"1left","list":"1"},{"item":"27","conditions":"ercf","read_time":[4725],"image_error":false,"slider_value":50,"leftright_trial":"1left","list":"1"},{"item":"33","conditions":"ferdf","read_time":[6707],"image_error":false,"slider_value":100,"leftright_trial":"1right","list":"1"},{"item":"23","conditions":"brdc","read_time":[5008],"image_error":false,"slider_value":50,"leftright_trial":"1left","list":"1"},{"item":"27","conditions":"brcf","read_time":[6516],"image_error":false,"slider_value":50,"leftright_trial":"1left","list":"1"},{"item":"30","conditions":"fbrdf","read_time":[16074],"image_error":false,"slider_value":5,"leftright_trial":"1left","list":"1"},{"item":"11","conditions":"zrdf","read_time":[5763],"image_error":false,"slider_value":50,"leftright_trial":"1left","list":"1"},{"item":"31","conditions":"ferdc","read_time":[11237],"image_error":false,"slider_value":97,"leftright_trial":"1right","list":"1"},{"item":"28","conditions":"fzrcf","read_time":[16303],"image_error":false,"slider_value":21,"leftright_trial":"1left","list":"1"},{"item":"37","conditions":"fercf","read_time":[12073],"image_error":false,"slider_value":2,"leftright_trial":"1left","list":"1"},{"item":"24","conditions":"ercf","read_time":[6132],"image_error":false,"slider_value":50,"leftright_trial":"1left","list":"1"},{"item":"36","conditions":"fercf","read_time":[5481],"image_error":false,"slider_value":1,"leftright_trial":"1left","list":"1"},{"item":"9","conditions":"erdf","read_time":[5125],"image_error":false,"slider_value":50,"leftright_trial":"1right","list":"1"},{"item":"29","conditions":"fbrdc","read_time":[7977],"image_error":false,"slider_value":2,"leftright_trial":"1left","list":"1"},{"item":"31","conditions":"fercf","read_time":[7068],"image_error":false,"slider_value":0,"leftright_trial":"1left","list":"1"},{"item":"34","conditions":"fercf","read_time":[8510],"image_error":false,"slider_value":97,"leftright_trial":"1right","list":"1"},{"item":"33","conditions":"fbrdf","read_time":[7006],"image_error":false,"slider_value":2,"leftright_trial":"1left","list":"1"},{"item":"4","conditions":"erdc","read_time":[6048],"image_error":false,"slider_value":55,"leftright_trial":"1left","list":"1"},{"item":"9","conditions":"brdf","read_time":[9626],"image_error":false,"slider_value":50,"leftright_trial":"1left","list":"1"},{"item":"35","conditions":"fercf","read_time":[5434],"image_error":false,"slider_value":3,"leftright_trial":"1left","list":"1"},{"item":"30","conditions":"ferdf","read_time":[10650],"image_error":false,"slider_value":68,"leftright_trial":"1right","list":"1"},{"item":"35","conditions":"fbrdc","read_time":[8750],"image_error":false,"slider_value":64,"leftright_trial":"1left","list":"1"},{"item":"4","conditions":"zrdc","read_time":[9709],"image_error":false,"slider_value":49,"leftright_trial":"1left","list":"1"},{"item":"29","conditions":"fbrcf","read_time":[10089],"image_error":false,"slider_value":1,"leftright_trial":"1left","list":"1"},{"item":"32","conditions":"fbrdf","read_time":[10874],"image_error":false,"slider_value":100,"leftright_trial":"1right","list":"1"},{"item":"33","conditions":"fercf","read_time":[8904],"image_error":false,"slider_value":0,"leftright_trial":"1left","list":"1"},{"item":"1","conditions":"brdc","read_time":[6120],"image_error":false,"slider_value":50,"leftright_trial":"1left","list":"1"},{"item":"35","conditions":"fzrdc","read_time":[6276],"image_error":false,"slider_value":1,"leftright_trial":"1right","list":"1"},{"item":"28","conditions":"ferdc","read_time":[10425],"image_error":false,"slider_value":21,"leftright_trial":"1left","list":"1"},{"item":"32","conditions":"fzrcf","read_time":[9607],"image_error":false,"slider_value":22,"leftright_trial":"1left","list":"1"},{"item":"22","conditions":"zrdf","read_time":[11246],"image_error":false,"slider_value":66,"leftright_trial":"1right","list":"1"},{"item":"16","conditions":"ercf","read_time":[10481],"image_error":false,"slider_value":52,"leftright_trial":"1left","list":"1"},{"item":"13","conditions":"ercf","read_time":[6545],"image_error":false,"slider_value":50,"leftright_trial":"1left","list":"1"},{"item":"28","conditions":"fzrdc","read_time":[7149],"image_error":false,"slider_value":66,"leftright_trial":"1left","list":"1"},{"item":"23","conditions":"zrdc","read_time":[7630],"image_error":false,"slider_value":50,"leftright_trial":"1right","list":"1"},{"item":"15","conditions":"zrdc","read_time":[6539],"image_error":false,"slider_value":50,"leftright_trial":"1right","list":"1"},{"item":"29","conditions":"ferdf","read_time":[8029],"image_error":false,"slider_value":3,"leftright_trial":"1left","list":"1"},{"item":"36","conditions":"fzrdc","read_time":[6317],"image_error":false,"slider_value":2,"leftright_trial":"1right","list":"1"},{"item":"21","conditions":"brcf","read_time":[5668],"image_error":false,"slider_value":50,"leftright_trial":"1right","list":"1"},{"item":"35","conditions":"fzrcf","read_time":[6430],"image_error":false,"slider_value":2,"leftright_trial":"1right","list":"1"},{"item":"15","conditions":"brdc","read_time":[7932],"image_error":false,"slider_value":52,"leftright_trial":"1left","list":"1"},{"item":"30","conditions":"fzrcf","read_time":[8188],"image_error":false,"slider_value":74,"leftright_trial":"1right","list":"1"},{"item":"13","conditions":"brcf","read_time":[7999],"image_error":false,"slider_value":50,"leftright_trial":"1left","list":"1"},{"item":"31","conditions":"fzrcf","read_time":[9478],"image_error":false,"slider_value":38,"leftright_trial":"1left","list":"1"},{"item":"38","conditions":"fzrdc","read_time":[5961],"image_error":false,"slider_value":99,"leftright_trial":"1left","list":"1"},{"item":"33","conditions":"fzrdf","read_time":[9307],"image_error":false,"slider_value":19,"leftright_trial":"1right","list":"1"},{"item":"35","conditions":"ferdf","read_time":[8146],"image_error":false,"slider_value":2,"leftright_trial":"1left","list":"1"},{"item":"8","conditions":"zrcf","read_time":[3605],"image_error":false,"slider_value":50,"leftright_trial":"1left","list":"1"},{"item":"1","conditions":"zrdc","read_time":[4845],"image_error":false,"slider_value":50,"leftright_trial":"1left","list":"1"},{"item":"8","conditions":"brcf","read_time":[5585],"image_error":false,"slider_value":50,"leftright_trial":"1left","list":"1"},{"item":"29","conditions":"fercf","read_time":[10009],"image_error":false,"slider_value":99,"leftright_trial":"1right","list":"1"},{"item":"21","conditions":"zrcf","read_time":[7039],"image_error":false,"slider_value":50,"leftright_trial":"1right","list":"1"},{"item":"31","conditions":"ferdf","read_time":[7340],"image_error":false,"slider_value":1,"leftright_trial":"1left","list":"1"},{"item":"38","conditions":"fzrcf","read_time":[8916],"image_error":false,"slider_value":61,"leftright_trial":"1left","list":"1"},{"item":"3","conditions":"brdf","read_time":[6342],"image_error":false,"slider_value":50,"leftright_trial":"1right","list":"1"},{"item":"29","conditions":"fzrcf","read_time":[8318],"image_error":false,"slider_value":24,"leftright_trial":"1right","list":"1"},{"item":"28","conditions":"fzrdf","read_time":[8509],"image_error":false,"slider_value":18,"leftright_trial":"1right","list":"1"},{"item":"6","conditions":"erdf","read_time":[8401],"image_error":false,"slider_value":50,"leftright_trial":"1left","list":"1"},{"item":"33","conditions":"ferdc","read_time":[7370],"image_error":false,"slider_value":100,"leftright_trial":"1right","list":"1"},{"item":"36","conditions":"ferdc","read_time":[9058],"image_error":false,"slider_value":1,"leftright_trial":"1left","list":"1"},{"item":"26","conditions":"erdc","read_time":[5200],"image_error":false,"slider_value":50,"leftright_trial":"1right","list":"1"},{"item":"34","conditions":"fbrdc","read_time":[13596],"image_error":false,"slider_value":63,"leftright_trial":"1left","list":"1"},{"item":"32","conditions":"fbrdc","read_time":[9506],"image_error":false,"slider_value":0,"leftright_trial":"1left","list":"1"},{"item":"35","conditions":"fbrdf","read_time":[12283],"image_error":false,"slider_value":74,"leftright_trial":"1left","list":"1"},{"item":"11","conditions":"brdf","read_time":[9530],"image_error":false,"slider_value":50,"leftright_trial":"1right","list":"1"},{"item":"37","conditions":"fbrcf","read_time":[12331],"image_error":false,"slider_value":43,"leftright_trial":"1left","list":"1"},{"item":"32","conditions":"fercf","read_time":[8079],"image_error":false,"slider_value":98,"leftright_trial":"1right","list":"1"},{"item":"34","conditions":"ferdc","read_time":[13359],"image_error":false,"slider_value":100,"leftright_trial":"1right","list":"1"},{"item":"32","conditions":"ferdf","read_time":[6697],"image_error":false,"slider_value":78,"leftright_trial":"1right","list":"1"},{"item":"35","conditions":"ferdc","read_time":[10818],"image_error":false,"slider_value":0,"leftright_trial":"1left","list":"1"},{"item":"31","conditions":"fbrdf","read_time":[8836],"image_error":false,"slider_value":98,"leftright_trial":"1right","list":"1"},{"item":"32","conditions":"ferdc","read_time":[11480],"image_error":false,"slider_value":98,"leftright_trial":"1right","list":"1"},{"item":"31","conditions":"fbrcf","read_time":[12206],"image_error":false,"slider_value":3,"leftright_trial":"1left","list":"1"},{"item":"18","conditions":"zrdc","read_time":[4955],"image_error":false,"slider_value":50,"leftright_trial":"1right","list":"1"},{"item":"30","conditions":"fbrdc","read_time":[4747],"image_error":false,"slider_value":97,"leftright_trial":"1right","list":"1"},{"item":"31","conditions":"fzrdc","read_time":[8834],"image_error":false,"slider_value":31,"leftright_trial":"1left","list":"1"},{"item":"14","conditions":"erdf","read_time":[5519],"image_error":false,"slider_value":50,"leftright_trial":"1left","list":"1"},{"item":"32","conditions":"fzrdc","read_time":[4171],"image_error":false,"slider_value":60,"leftright_trial":"1right","list":"1"},{"item":"36","conditions":"fbrcf","read_time":[17152],"image_error":false,"slider_value":39,"leftright_trial":"1right","list":"1"},{"item":"18","conditions":"erdc","read_time":[4849],"image_error":false,"slider_value":50,"leftright_trial":"1right","list":"1"},{"item":"33","conditions":"fzrcf","read_time":[9609],"image_error":false,"slider_value":70,"leftright_trial":"1left","list":"1"},{"item":"30","conditions":"fbrcf","read_time":[7030],"image_error":false,"slider_value":98,"leftright_trial":"1right","list":"1"},{"item":"3","conditions":"erdf","read_time":[5988],"image_error":false,"slider_value":50,"leftright_trial":"1right","list":"1"},{"item":"38","conditions":"fercf","read_time":[7491],"image_error":false,"slider_value":0,"leftright_trial":"1left","list":"1"},{"item":"16","conditions":"brcf","read_time":[7051],"image_error":false,"slider_value":50,"leftright_trial":"1left","list":"1"},{"item":"35","conditions":"fzrdf","read_time":[7978],"image_error":false,"slider_value":0,"leftright_trial":"1right","list":"1"},{"item":"14","conditions":"zrdf","read_time":[5041],"image_error":false,"slider_value":50,"leftright_trial":"1right","list":"1"},{"item":"30","conditions":"fzrdf","read_time":[10730],"image_error":false,"slider_value":79,"leftright_trial":"1left","list":"1"},{"item":"34","conditions":"fzrcf","read_time":[11860],"image_error":false,"slider_value":100,"leftright_trial":"1left","list":"1"},{"item":"12","conditions":"brdc","read_time":[4131],"image_error":false,"slider_value":50,"leftright_trial":"1left","list":"1"},{"item":"36","conditions":"fbrdc","read_time":[6500],"image_error":false,"slider_value":64,"leftright_trial":"1left","list":"1"},{"item":"29","conditions":"fzrdf","read_time":[7531],"image_error":false,"slider_value":0,"leftright_trial":"1right","list":"1"},{"item":"10","conditions":"ercf","read_time":[4430],"image_error":false,"slider_value":50,"leftright_trial":"1left","list":"1"},{"item":"28","conditions":"fercf","read_time":[6295],"image_error":false,"slider_value":100,"leftright_trial":"1right","list":"1"},{"item":"25","conditions":"erdf","read_time":[12798],"image_error":false,"slider_value":50,"leftright_trial":"1left","list":"1"},{"item":"28","conditions":"ferdf","read_time":[6711],"image_error":false,"slider_value":30,"leftright_trial":"1left","list":"1"},{"item":"24","conditions":"zrcf","read_time":[4025],"image_error":false,"slider_value":50,"leftright_trial":"1left","list":"1"},{"item":"11","conditions":"erdf","read_time":[7764],"image_error":false,"slider_value":50,"leftright_trial":"1left","list":"1"},{"item":"20","conditions":"brdc","read_time":[9746],"image_error":false,"slider_value":50,"leftright_trial":"1right","list":"1"},{"item":"18","conditions":"brdc","read_time":[5639],"image_error":false,"slider_value":50,"leftright_trial":"1left","list":"1"},{"item":"8","conditions":"ercf","read_time":[4217],"image_error":false,"slider_value":50,"leftright_trial":"1left","list":"1"},{"item":"33","conditions":"fzrdc","read_time":[7232],"image_error":false,"slider_value":18,"leftright_trial":"1right","list":"1"},{"item":"16","conditions":"zrcf","read_time":[11850],"image_error":false,"slider_value":50,"leftright_trial":"1left","list":"1"},{"item":"38","conditions":"ferdf","read_time":[7549],"image_error":false,"slider_value":96,"leftright_trial":"1right","list":"1"},{"item":"24","conditions":"brcf","read_time":[6003],"image_error":false,"slider_value":50,"leftright_trial":"1left","list":"1"},{"item":"31","conditions":"fbrdc","read_time":[9219],"image_error":false,"slider_value":99,"leftright_trial":"1right","list":"1"},{"item":"17","conditions":"zrdf","read_time":[4340],"image_error":false,"slider_value":50,"leftright_trial":"1right","list":"1"},{"item":"29","conditions":"fbrdf","read_time":[9695],"image_error":false,"slider_value":100,"leftright_trial":"1right","list":"1"},{"item":"34","conditions":"fzrdf","read_time":[8363],"image_error":false,"slider_value":100,"leftright_trial":"1left","list":"1"},{"item":"29","conditions":"fzrdc","read_time":[2290,15317],"image_error":false,"slider_value":83,"leftright_trial":"1left","list":"1"},{"item":"29","conditions":"ferdc","read_time":[9688],"image_error":false,"slider_value":0,"leftright_trial":"1left","list":"1"},{"item":"7","conditions":"zrdc","read_time":[6557],"image_error":false,"slider_value":50,"leftright_trial":"1left","list":"1"},{"item":"14","conditions":"brdf","read_time":[5664],"image_error":false,"slider_value":50,"leftright_trial":"1right","list":"1"}],"id":"624201f30f1aa0","catch_trials":[],"block_boundaries":[46,90,136],"system":{"Browser":"Chrome","OS":"Windows","screenH":864,"screenW":1536},"condition":"L","subject_information":{"language":"Deutsch","asses":"Yes","age":"50","gender":"Female","comments":"","fluent":"No"},"time_in_minutes":33.90351666666667,"missed_break_one":false,"missed_break_two":false,"missed_break_three":false}