{"trials":[{"item":"39","conditions":"uzrdf","read_time":[20063],"image_error":false,"slider_value":-1,"leftright_trial":"1right","list":"7"},{"item":"39","conditions":"uerdc","read_time":[16869],"image_error":false,"slider_value":0,"leftright_trial":"1right","list":"7"},{"item":"39","conditions":"ubrcf","read_time":[9184],"image_error":false,"slider_value":-1,"leftright_trial":"1left","list":"7"},{"item":"2","conditions":"zrcf","read_time":[6463],"image_error":false,"slider_value":0,"leftright_trial":"1right","list":"4"},{"item":"29","conditions":"fercf","read_time":[5194],"image_error":false,"slider_value":0,"leftright_trial":"1left","list":"4"},{"item":"38","conditions":"fercf","read_time":[5522],"image_error":false,"slider_value":100,"leftright_trial":"1right","list":"4"},{"item":"25","conditions":"zrdf","read_time":[6850],"image_error":false,"slider_value":0,"leftright_trial":"1left","list":"4"},{"item":"29","conditions":"fzrdc","read_time":[3883],"image_error":false,"slider_value":0,"leftright_trial":"1left","list":"4"},{"item":"4","conditions":"erdc","read_time":[3153],"image_error":false,"slider_value":0,"leftright_trial":"1left","list":"4"},{"item":"38","conditions":"fzrcf","read_time":[6827],"image_error":false,"slider_value":-1,"leftright_trial":"1left","list":"4"},{"item":"35","conditions":"ferdc","read_time":[5667],"image_error":false,"slider_value":0,"leftright_trial":"1left","list":"4"},{"item":"38","conditions":"fbrdf","read_time":[6260],"image_error":false,"slider_value":-1,"leftright_trial":"1right","list":"4"},{"item":"38","conditions":"ferdf","read_time":[5211],"image_error":false,"slider_value":100,"leftright_trial":"1right","list":"4"},{"item":"38","conditions":"fzrdc","read_time":[3831],"image_error":false,"slider_value":0,"leftright_trial":"1right","list":"4"},{"item":"20","conditions":"erdc","read_time":[4700],"image_error":false,"slider_value":-1,"leftright_trial":"1left","list":"4"},{"item":"34","conditions":"fbrdc","read_time":[5042],"image_error":false,"slider_value":-1,"leftright_trial":"1left","list":"4"},{"item":"19","conditions":"erdf","read_time":[16907],"image_error":false,"slider_value":0,"leftright_trial":"1left","list":"4"},{"item":"31","conditions":"fzrcf","read_time":[4173],"image_error":false,"slider_value":0,"leftright_trial":"1left","list":"4"},{"item":"32","conditions":"fbrdf","read_time":[6565],"image_error":false,"slider_value":0,"leftright_trial":"1left","list":"4"},{"item":"32","conditions":"fzrcf","read_time":[4107],"image_error":false,"slider_value":0,"leftright_trial":"1right","list":"4"},{"item":"17","conditions":"brdf","read_time":[4211],"image_error":false,"slider_value":0,"leftright_trial":"1right","list":"4"},{"item":"36","conditions":"ferdf","read_time":[2813],"image_error":false,"slider_value":0,"leftright_trial":"1right","list":"4"},{"item":"28","conditions":"ferdc","read_time":[3391],"image_error":false,"slider_value":0,"leftright_trial":"1right","list":"4"},{"item":"25","conditions":"brdf","read_time":[3057],"image_error":false,"slider_value":0,"leftright_trial":"1left","list":"4"},{"item":"7","conditions":"brdc","read_time":[6006],"image_error":false,"slider_value":-1,"leftright_trial":"1right","list":"4"},{"item":"29","conditions":"fzrcf","read_time":[3507],"image_error":false,"slider_value":0,"leftright_trial":"1left","list":"4"},{"item":"38","conditions":"ferdc","read_time":[2515],"image_error":false,"slider_value":0,"leftright_trial":"1left","list":"4"},{"item":"24","conditions":"zrcf","read_time":[3035],"image_error":false,"slider_value":0,"leftright_trial":"1right","list":"4"},{"item":"36","conditions":"fercf","read_time":[4397],"image_error":false,"slider_value":100,"leftright_trial":"1right","list":"4"},{"item":"24","conditions":"ercf","read_time":[3884],"image_error":false,"slider_value":0,"leftright_trial":"1left","list":"4"},{"item":"37","conditions":"ferdf","read_time":[4048],"image_error":false,"slider_value":100,"leftright_trial":"1right","list":"4"},{"item":"17","conditions":"zrdf","read_time":[2675],"image_error":false,"slider_value":0,"leftright_trial":"1left","list":"4"},{"item":"35","conditions":"fbrcf","read_time":[6430],"image_error":false,"slider_value":-1,"leftright_trial":"1right","list":"4"},{"item":"34","conditions":"fbrcf","read_time":[5576],"image_error":false,"slider_value":-1,"leftright_trial":"1right","list":"4"},{"item":"34","conditions":"ferdf","read_time":[5394],"image_error":false,"slider_value":100,"leftright_trial":"1right","list":"4"},{"item":"27","conditions":"zrcf","read_time":[5812],"image_error":false,"slider_value":0,"leftright_trial":"1left","list":"4"},{"item":"6","conditions":"erdf","read_time":[3409],"image_error":false,"slider_value":0,"leftright_trial":"1left","list":"4"},{"item":"36","conditions":"fbrcf","read_time":[7388],"image_error":false,"slider_value":-1,"leftright_trial":"1left","list":"4"},{"item":"15","conditions":"brdc","read_time":[3787],"image_error":false,"slider_value":0,"leftright_trial":"1right","list":"4"},{"item":"30","conditions":"fzrdf","read_time":[5051],"image_error":false,"slider_value":0,"leftright_trial":"1right","list":"4"},{"item":"14","conditions":"brdf","read_time":[2756],"image_error":false,"slider_value":0,"leftright_trial":"1right","list":"4"},{"item":"10","conditions":"ercf","read_time":[4402],"image_error":false,"slider_value":0,"leftright_trial":"1left","list":"4"},{"item":"35","conditions":"fzrdc","read_time":[2420],"image_error":false,"slider_value":0,"leftright_trial":"1right","list":"4"},{"item":"35","conditions":"fercf","read_time":[3571],"image_error":false,"slider_value":100,"leftright_trial":"1right","list":"4"},{"item":"37","conditions":"ferdc","read_time":[4821],"image_error":false,"slider_value":100,"leftright_trial":"1right","list":"4"},{"item":"30","conditions":"ferdc","read_time":[5986],"image_error":false,"slider_value":-1,"leftright_trial":"1left","list":"4"},{"item":"5","conditions":"ercf","read_time":[3219],"image_error":false,"slider_value":0,"leftright_trial":"1right","list":"4"},{"item":"31","conditions":"fbrdf","read_time":[6053],"image_error":false,"slider_value":-1,"leftright_trial":"1left","list":"4"},{"item":"1","conditions":"erdc","read_time":[4628],"image_error":false,"slider_value":0,"leftright_trial":"1left","list":"4"},{"item":"28","conditions":"fercf","read_time":[2043],"image_error":false,"slider_value":0,"leftright_trial":"1right","list":"4"},{"item":"21","conditions":"brcf","read_time":[5369],"image_error":false,"slider_value":0,"leftright_trial":"1right","list":"4"},{"item":"31","conditions":"fzrdc","read_time":[2546],"image_error":false,"slider_value":0,"leftright_trial":"1right","list":"4"},{"item":"32","conditions":"fbrdc","read_time":[3627],"image_error":false,"slider_value":0,"leftright_trial":"1left","list":"4"},{"item":"32","conditions":"fercf","read_time":[3154],"image_error":false,"slider_value":0,"leftright_trial":"1right","list":"4"},{"item":"37","conditions":"fzrcf","read_time":[4346],"image_error":false,"slider_value":100,"leftright_trial":"1left","list":"4"},{"item":"33","conditions":"fbrcf","read_time":[2892],"image_error":false,"slider_value":0,"leftright_trial":"1left","list":"4"},{"item":"38","conditions":"fzrdf","read_time":[2923],"image_error":false,"slider_value":0,"leftright_trial":"1right","list":"4"},{"item":"18","conditions":"erdc","read_time":[2755],"image_error":false,"slider_value":0,"leftright_trial":"1right","list":"4"},{"item":"37","conditions":"fbrcf","read_time":[6067],"image_error":false,"slider_value":-1,"leftright_trial":"1left","list":"4"},{"item":"11","conditions":"erdf","read_time":[4469],"image_error":false,"slider_value":0,"leftright_trial":"1right","list":"4"},{"item":"37","conditions":"fzrdf","read_time":[2619],"image_error":false,"slider_value":0,"leftright_trial":"1right","list":"4"},{"item":"18","conditions":"zrdc","read_time":[2275],"image_error":false,"slider_value":0,"leftright_trial":"1right","list":"4"},{"item":"16","conditions":"zrcf","read_time":[3173],"image_error":false,"slider_value":0,"leftright_trial":"1right","list":"4"},{"item":"3","conditions":"zrdf","read_time":[2435],"image_error":false,"slider_value":0,"leftright_trial":"1right","list":"4"},{"item":"38","conditions":"fbrdc","read_time":[6163],"image_error":false,"slider_value":-1,"leftright_trial":"1right","list":"4"},{"item":"2","conditions":"ercf","read_time":[3028],"image_error":false,"slider_value":0,"leftright_trial":"1right","list":"4"},{"item":"21","conditions":"zrcf","read_time":[2914],"image_error":false,"slider_value":0,"leftright_trial":"1left","list":"4"},{"item":"22","conditions":"zrdf","read_time":[4180],"image_error":false,"slider_value":0,"leftright_trial":"1right","list":"4"},{"item":"29","conditions":"fbrdf","read_time":[7865],"image_error":false,"slider_value":100,"leftright_trial":"1right","list":"4"},{"item":"23","conditions":"zrdc","read_time":[5427],"image_error":false,"slider_value":0,"leftright_trial":"1left","list":"4"},{"item":"36","conditions":"ferdc","read_time":[3962],"image_error":false,"slider_value":0,"leftright_trial":"1left","list":"4"},{"item":"31","conditions":"ferdf","read_time":[3781],"image_error":false,"slider_value":0,"leftright_trial":"1left","list":"4"},{"item":"2","conditions":"brcf","read_time":[3516],"image_error":false,"slider_value":0,"leftright_trial":"1right","list":"4"},{"item":"33","conditions":"fzrcf","read_time":[3412],"image_error":false,"slider_value":0,"leftright_trial":"1right","list":"4"},{"item":"35","conditions":"fzrcf","read_time":[3580],"image_error":false,"slider_value":100,"leftright_trial":"1left","list":"4"},{"item":"32","conditions":"fzrdc","read_time":[2188],"image_error":false,"slider_value":0,"leftright_trial":"1right","list":"4"},{"item":"30","conditions":"fercf","read_time":[4417],"image_error":false,"slider_value":0,"leftright_trial":"1left","list":"4"},{"item":"29","conditions":"fbrcf","read_time":[3293],"image_error":false,"slider_value":100,"leftright_trial":"1right","list":"4"},{"item":"9","conditions":"brdf","read_time":[4648],"image_error":false,"slider_value":0,"leftright_trial":"1right","list":"4"},{"item":"8","conditions":"brcf","read_time":[4365],"image_error":false,"slider_value":0,"leftright_trial":"1left","list":"4"},{"item":"37","conditions":"fbrdc","read_time":[5473],"image_error":false,"slider_value":-1,"leftright_trial":"1right","list":"4"},{"item":"27","conditions":"brcf","read_time":[3514],"image_error":false,"slider_value":0,"leftright_trial":"1left","list":"4"},{"item":"31","conditions":"fzrdf","read_time":[4339],"image_error":false,"slider_value":0,"leftright_trial":"1left","list":"4"},{"item":"33","conditions":"fbrdf","read_time":[4561],"image_error":false,"slider_value":100,"leftright_trial":"1right","list":"4"},{"item":"11","conditions":"zrdf","read_time":[3017],"image_error":false,"slider_value":0,"leftright_trial":"1right","list":"4"},{"item":"29","conditions":"fbrdc","read_time":[5522],"image_error":false,"slider_value":0,"leftright_trial":"1left","list":"4"},{"item":"38","conditions":"fbrcf","read_time":[5955],"image_error":false,"slider_value":-1,"leftright_trial":"1left","list":"4"},{"item":"9","conditions":"erdf","read_time":[4235],"image_error":false,"slider_value":0,"leftright_trial":"1left","list":"4"},{"item":"32","conditions":"fzrdf","read_time":[2499],"image_error":false,"slider_value":0,"leftright_trial":"1right","list":"4"},{"item":"28","conditions":"fbrdc","read_time":[4394],"image_error":false,"slider_value":100,"leftright_trial":"1right","list":"4"},{"item":"7","conditions":"zrdc","read_time":[2474],"image_error":false,"slider_value":0,"leftright_trial":"1left","list":"4"},{"item":"33","conditions":"fzrdc","read_time":[2571],"image_error":false,"slider_value":0,"leftright_trial":"1left","list":"4"},{"item":"23","conditions":"brdc","read_time":[3136],"image_error":false,"slider_value":0,"leftright_trial":"1right","list":"4"},{"item":"9","conditions":"zrdf","read_time":[4245],"image_error":false,"slider_value":0,"leftright_trial":"1right","list":"4"},{"item":"33","conditions":"fercf","read_time":[2027],"image_error":false,"slider_value":0,"leftright_trial":"1left","list":"4"},{"item":"7","conditions":"erdc","read_time":[2018],"image_error":false,"slider_value":0,"leftright_trial":"1right","list":"4"},{"item":"11","conditions":"brdf","read_time":[5748],"image_error":false,"slider_value":0,"leftright_trial":"1left","list":"4"},{"item":"10","conditions":"brcf","read_time":[3580],"image_error":false,"slider_value":0,"leftright_trial":"1left","list":"4"},{"item":"6","conditions":"zrdf","read_time":[3403],"image_error":false,"slider_value":0,"leftright_trial":"1right","list":"4"},{"item":"28","conditions":"fzrcf","read_time":[2571],"image_error":false,"slider_value":0,"leftright_trial":"1left","list":"4"},{"item":"35","conditions":"fbrdc","read_time":[7499],"image_error":false,"slider_value":-1,"leftright_trial":"1left","list":"4"},{"item":"30","conditions":"fzrcf","read_time":[2874],"image_error":false,"slider_value":0,"leftright_trial":"1left","list":"4"},{"item":"18","conditions":"brdc","read_time":[3133],"image_error":false,"slider_value":0,"leftright_trial":"1right","list":"4"},{"item":"34","conditions":"ferdc","read_time":[2411],"image_error":false,"slider_value":0,"leftright_trial":"1left","list":"4"},{"item":"30","conditions":"fzrdc","read_time":[2172],"image_error":false,"slider_value":0,"leftright_trial":"1right","list":"4"},{"item":"32","conditions":"fbrcf","read_time":[3243],"image_error":false,"slider_value":0,"leftright_trial":"1left","list":"4"},{"item":"31","conditions":"ferdc","read_time":[2382],"image_error":false,"slider_value":0,"leftright_trial":"1left","list":"4"},{"item":"8","conditions":"zrcf","read_time":[3128],"image_error":false,"slider_value":0,"leftright_trial":"1right","list":"4"},{"item":"24","conditions":"brcf","read_time":[2219],"image_error":false,"slider_value":0,"leftright_trial":"1left","list":"4"},{"item":"3","conditions":"brdf","read_time":[2240],"image_error":false,"slider_value":0,"leftright_trial":"1left","list":"4"},{"item":"29","conditions":"ferdc","read_time":[4618],"image_error":false,"slider_value":0,"leftright_trial":"1left","list":"4"},{"item":"32","conditions":"ferdf","read_time":[5676],"image_error":false,"slider_value":100,"leftright_trial":"1right","list":"4"},{"item":"27","conditions":"ercf","read_time":[3061],"image_error":false,"slider_value":0,"leftright_trial":"1right","list":"4"},{"item":"4","conditions":"zrdc","read_time":[4325],"image_error":false,"slider_value":0,"leftright_trial":"1left","list":"4"},{"item":"36","conditions":"fbrdc","read_time":[6057],"image_error":false,"slider_value":-1,"leftright_trial":"1right","list":"4"},{"item":"28","conditions":"ferdf","read_time":[4018],"image_error":false,"slider_value":0,"leftright_trial":"1right","list":"4"},{"item":"30","conditions":"fbrcf","read_time":[2870],"image_error":false,"slider_value":0,"leftright_trial":"1left","list":"4"},{"item":"35","conditions":"fbrdf","read_time":[6909],"image_error":false,"slider_value":-1,"leftright_trial":"1left","list":"4"},{"item":"37","conditions":"fzrdc","read_time":[4232],"image_error":false,"slider_value":100,"leftright_trial":"1left","list":"4"},{"item":"33","conditions":"fbrdc","read_time":[4628],"image_error":false,"slider_value":0,"leftright_trial":"1left","list":"4"},{"item":"15","conditions":"erdc","read_time":[4195],"image_error":false,"slider_value":0,"leftright_trial":"1left","list":"4"},{"item":"29","conditions":"ferdf","read_time":[4322],"image_error":false,"slider_value":100,"leftright_trial":"1right","list":"4"},{"item":"37","conditions":"fercf","read_time":[2363],"image_error":false,"slider_value":0,"leftright_trial":"1left","list":"4"},{"item":"31","conditions":"fbrdc","read_time":[5676],"image_error":false,"slider_value":100,"leftright_trial":"1right","list":"4"},{"item":"13","conditions":"zrcf","read_time":[3868],"image_error":false,"slider_value":100,"leftright_trial":"1left","list":"4"},{"item":"12","conditions":"erdc","read_time":[2925],"image_error":false,"slider_value":100,"leftright_trial":"1right","list":"4"},{"item":"36","conditions":"fzrcf","read_time":[4428],"image_error":false,"slider_value":0,"leftright_trial":"1right","list":"4"},{"item":"32","conditions":"ferdc","read_time":[3812],"image_error":false,"slider_value":0,"leftright_trial":"1left","list":"4"},{"item":"20","conditions":"brdc","read_time":[2796],"image_error":false,"slider_value":0,"leftright_trial":"1right","list":"4"},{"item":"13","conditions":"ercf","read_time":[3692],"image_error":false,"slider_value":0,"leftright_trial":"1left","list":"4"},{"item":"35","conditions":"fzrdf","read_time":[2556],"image_error":false,"slider_value":0,"leftright_trial":"1right","list":"4"},{"item":"5","conditions":"zrcf","read_time":[2940],"image_error":false,"slider_value":0,"leftright_trial":"1right","list":"4"},{"item":"22","conditions":"erdf","read_time":[2387],"image_error":false,"slider_value":0,"leftright_trial":"1left","list":"4"},{"item":"16","conditions":"brcf","read_time":[4627],"image_error":false,"slider_value":0,"leftright_trial":"1left","list":"4"},{"item":"19","conditions":"brdf","read_time":[3220],"image_error":false,"slider_value":0,"leftright_trial":"1left","list":"4"},{"item":"35","conditions":"ferdf","read_time":[3101],"image_error":false,"slider_value":0,"leftright_trial":"1left","list":"4"},{"item":"15","conditions":"zrdc","read_time":[2241],"image_error":false,"slider_value":0,"leftright_trial":"1left","list":"4"},{"item":"14","conditions":"zrdf","read_time":[2259],"image_error":false,"slider_value":0,"leftright_trial":"1left","list":"4"},{"item":"17","conditions":"erdf","read_time":[3173],"image_error":false,"slider_value":0,"leftright_trial":"1right","list":"4"},{"item":"29","conditions":"fzrdf","read_time":[2757],"image_error":false,"slider_value":0,"leftright_trial":"1right","list":"4"},{"item":"30","conditions":"fbrdf","read_time":[3299],"image_error":false,"slider_value":100,"leftright_trial":"1right","list":"4"},{"item":"14","conditions":"erdf","read_time":[3468],"image_error":false,"slider_value":0,"leftright_trial":"1right","list":"4"},{"item":"19","conditions":"zrdf","read_time":[4276],"image_error":false,"slider_value":0,"leftright_trial":"1right","list":"4"},{"item":"20","conditions":"zrdc","read_time":[2675],"image_error":false,"slider_value":0,"leftright_trial":"1right","list":"4"},{"item":"34","conditions":"fzrcf","read_time":[4232],"image_error":false,"slider_value":100,"leftright_trial":"1left","list":"4"},{"item":"16","conditions":"ercf","read_time":[4475],"image_error":false,"slider_value":0,"leftright_trial":"1right","list":"4"},{"item":"4","conditions":"brdc","read_time":[3324],"image_error":false,"slider_value":0,"leftright_trial":"1left","list":"4"},{"item":"10","conditions":"zrcf","read_time":[2876],"image_error":false,"slider_value":0,"leftright_trial":"1right","list":"4"},{"item":"8","conditions":"ercf","read_time":[3231],"image_error":false,"slider_value":0,"leftright_trial":"1right","list":"4"},{"item":"34","conditions":"fzrdf","read_time":[4425],"image_error":false,"slider_value":100,"leftright_trial":"1left","list":"4"},{"item":"33","conditions":"fzrdf","read_time":[2772],"image_error":false,"slider_value":0,"leftright_trial":"1right","list":"4"},{"item":"26","conditions":"brdc","read_time":[2902],"image_error":false,"slider_value":0,"leftright_trial":"1right","list":"4"},{"item":"36","conditions":"fbrdf","read_time":[6432],"image_error":false,"slider_value":-1,"leftright_trial":"1right","list":"4"},{"item":"3","conditions":"erdf","read_time":[2852],"image_error":false,"slider_value":0,"leftright_trial":"1right","list":"4"},{"item":"28","conditions":"fbrdf","read_time":[3292],"image_error":false,"slider_value":0,"leftright_trial":"1left","list":"4"},{"item":"34","conditions":"fercf","read_time":[2140],"image_error":false,"slider_value":0,"leftright_trial":"1left","list":"4"},{"item":"25","conditions":"erdf","read_time":[13617],"image_error":false,"slider_value":0,"leftright_trial":"1left","list":"4"},{"item":"21","conditions":"ercf","read_time":[3824],"image_error":false,"slider_value":0,"leftright_trial":"1left","list":"4"},{"item":"6","conditions":"brdf","read_time":[4080],"image_error":false,"slider_value":0,"leftright_trial":"1left","list":"4"},{"item":"13","conditions":"brcf","read_time":[5209],"image_error":false,"slider_value":0,"leftright_trial":"1left","list":"4"},{"item":"33","conditions":"ferdc","read_time":[5266],"image_error":false,"slider_value":100,"leftright_trial":"1right","list":"4"},{"item":"36","conditions":"fzrdc","read_time":[5420],"image_error":false,"slider_value":100,"leftright_trial":"1left","list":"4"},{"item":"1","conditions":"zrdc","read_time":[2884],"image_error":false,"slider_value":0,"leftright_trial":"1right","list":"4"},{"item":"22","conditions":"brdf","read_time":[3570],"image_error":false,"slider_value":0,"leftright_trial":"1left","list":"4"},{"item":"31","conditions":"fercf","read_time":[3963],"image_error":false,"slider_value":0,"leftright_trial":"1left","list":"4"},{"item":"26","conditions":"zrdc","read_time":[2564],"image_error":false,"slider_value":0,"leftright_trial":"1left","list":"4"},{"item":"1","conditions":"brdc","read_time":[3828],"image_error":false,"slider_value":0,"leftright_trial":"1right","list":"4"},{"item":"33","conditions":"ferdf","read_time":[3195],"image_error":false,"slider_value":0,"leftright_trial":"1left","list":"4"},{"item":"28","conditions":"fzrdc","read_time":[3556],"image_error":false,"slider_value":0,"leftright_trial":"1left","list":"4"},{"item":"5","conditions":"brcf","read_time":[3492],"image_error":false,"slider_value":0,"leftright_trial":"1left","list":"4"},{"item":"26","conditions":"erdc","read_time":[2907],"image_error":false,"slider_value":0,"leftright_trial":"1left","list":"4"},{"item":"34","conditions":"fzrdc","read_time":[4765],"image_error":false,"slider_value":0,"leftright_trial":"1right","list":"4"},{"item":"31","conditions":"fbrcf","read_time":[5812],"image_error":false,"slider_value":100,"leftright_trial":"1right","list":"4"},{"item":"30","conditions":"ferdf","read_time":[4840],"image_error":false,"slider_value":0,"leftright_trial":"1left","list":"4"},{"item":"28","conditions":"fbrcf","read_time":[6245],"image_error":false,"slider_value":100,"leftright_trial":"1right","list":"4"},{"item":"30","conditions":"fbrdc","read_time":[7427],"image_error":false,"slider_value":100,"leftright_trial":"1right","list":"4"},{"item":"12","conditions":"zrdc","read_time":[3139],"image_error":false,"slider_value":0,"leftright_trial":"1right","list":"4"},{"item":"12","conditions":"brdc","read_time":[2299],"image_error":false,"slider_value":0,"leftright_trial":"1right","list":"4"},{"item":"36","conditions":"fzrdf","read_time":[3717],"image_error":false,"slider_value":0,"leftright_trial":"1right","list":"4"},{"item":"34","conditions":"fbrdf","read_time":[5340],"image_error":false,"slider_value":-1,"leftright_trial":"1left","list":"4"},{"item":"37","conditions":"fbrdf","read_time":[4995],"image_error":false,"slider_value":-1,"leftright_trial":"1right","list":"4"},{"item":"23","conditions":"erdc","read_time":[14830],"image_error":false,"slider_value":0,"leftright_trial":"1left","list":"4"},{"item":"28","conditions":"fzrdf","read_time":[4260],"image_error":false,"slider_value":0,"leftright_trial":"1right","list":"4"}],"id":"6242cae14bc6a8","catch_trials":[],"block_boundaries":[38,90,128],"system":{"Browser":"Chrome","OS":"Windows","screenH":1080,"screenW":1920},"condition":"S","subject_information":{"language":"deutsch","asses":"Yes","age":"33","gender":"Male","comments":"","fluent":"No"},"time_in_minutes":31.609516666666668,"missed_break_one":false,"missed_break_two":false,"missed_break_three":false}