{"trials":[{"item":"39","conditions":"uerdc","read_time":[23230],"image_error":false,"slider_value":1,"leftright_trial":"1left","list":"7"},{"item":"39","conditions":"uzrdf","read_time":[7948],"image_error":false,"slider_value":1,"leftright_trial":"1right","list":"7"},{"item":"39","conditions":"ubrcf","read_time":[9840],"image_error":false,"slider_value":1,"leftright_trial":"1right","list":"7"},{"item":"38","conditions":"fbrdf","read_time":[6032],"image_error":false,"slider_value":99,"leftright_trial":"1right","list":"4"},{"item":"34","conditions":"fzrdf","read_time":[5924],"image_error":false,"slider_value":97,"leftright_trial":"1left","list":"4"},{"item":"29","conditions":"fzrdc","read_time":[4556],"image_error":false,"slider_value":2,"leftright_trial":"1right","list":"4"},{"item":"12","conditions":"zrdc","read_time":[5128],"image_error":false,"slider_value":99,"leftright_trial":"1left","list":"4"},{"item":"32","conditions":"fbrdc","read_time":[7366],"image_error":false,"slider_value":0,"leftright_trial":"1left","list":"4"},{"item":"26","conditions":"brdc","read_time":[7622],"image_error":false,"slider_value":2,"leftright_trial":"1left","list":"4"},{"item":"28","conditions":"fzrdf","read_time":[8148],"image_error":false,"slider_value":1,"leftright_trial":"1right","list":"4"},{"item":"4","conditions":"brdc","read_time":[5672],"image_error":false,"slider_value":1,"leftright_trial":"1left","list":"4"},{"item":"37","conditions":"ferdc","read_time":[4656],"image_error":false,"slider_value":1,"leftright_trial":"1left","list":"4"},{"item":"32","conditions":"fzrdf","read_time":[9906],"image_error":false,"slider_value":98,"leftright_trial":"1left","list":"4"},{"item":"32","conditions":"fbrdf","read_time":[5835],"image_error":false,"slider_value":2,"leftright_trial":"1left","list":"4"},{"item":"29","conditions":"fzrdf","read_time":[3627],"image_error":false,"slider_value":2,"leftright_trial":"1right","list":"4"},{"item":"34","conditions":"fbrdf","read_time":[15017],"image_error":false,"slider_value":-1,"leftright_trial":"1right","list":"4"},{"item":"29","conditions":"ferdf","read_time":[4996],"image_error":false,"slider_value":2,"leftright_trial":"1left","list":"4"},{"item":"30","conditions":"fzrdc","read_time":[2337],"image_error":false,"slider_value":2,"leftright_trial":"1right","list":"4"},{"item":"4","conditions":"erdc","read_time":[9644],"image_error":false,"slider_value":98,"leftright_trial":"1right","list":"4"},{"item":"33","conditions":"fzrdc","read_time":[4489],"image_error":false,"slider_value":2,"leftright_trial":"1right","list":"4"},{"item":"29","conditions":"fercf","read_time":[3740],"image_error":false,"slider_value":98,"leftright_trial":"1right","list":"4"},{"item":"36","conditions":"ferdf","read_time":[4664],"image_error":false,"slider_value":1,"leftright_trial":"1left","list":"4"},{"item":"37","conditions":"fercf","read_time":[2230],"image_error":false,"slider_value":1,"leftright_trial":"1left","list":"4"},{"item":"25","conditions":"erdf","read_time":[6279],"image_error":false,"slider_value":98,"leftright_trial":"1right","list":"4"},{"item":"21","conditions":"ercf","read_time":[3940],"image_error":false,"slider_value":2,"leftright_trial":"1left","list":"4"},{"item":"22","conditions":"erdf","read_time":[29816],"image_error":false,"slider_value":2,"leftright_trial":"1left","list":"4"},{"item":"15","conditions":"erdc","read_time":[11041],"image_error":false,"slider_value":78,"leftright_trial":"1right","list":"4"},{"item":"31","conditions":"fbrdf","read_time":[7696],"image_error":false,"slider_value":2,"leftright_trial":"1left","list":"4"},{"item":"28","conditions":"fzrdc","read_time":[2499],"image_error":false,"slider_value":2,"leftright_trial":"1right","list":"4"},{"item":"34","conditions":"ferdf","read_time":[3516],"image_error":false,"slider_value":3,"leftright_trial":"1left","list":"4"},{"item":"28","conditions":"fercf","read_time":[4805],"image_error":false,"slider_value":80,"leftright_trial":"1left","list":"4"},{"item":"38","conditions":"ferdc","read_time":[4865],"image_error":false,"slider_value":1,"leftright_trial":"1left","list":"4"},{"item":"30","conditions":"fbrdc","read_time":[5168],"image_error":false,"slider_value":98,"leftright_trial":"1right","list":"4"},{"item":"30","conditions":"fzrdf","read_time":[5084],"image_error":false,"slider_value":2,"leftright_trial":"1right","list":"4"},{"item":"28","conditions":"fbrcf","read_time":[5689],"image_error":false,"slider_value":2,"leftright_trial":"1left","list":"4"},{"item":"38","conditions":"fbrdc","read_time":[2955],"image_error":false,"slider_value":2,"leftright_trial":"1right","list":"4"},{"item":"14","conditions":"erdf","read_time":[15561],"image_error":false,"slider_value":-1,"leftright_trial":"1right","list":"4"},{"item":"37","conditions":"fbrdc","read_time":[10953],"image_error":false,"slider_value":-1,"leftright_trial":"1left","list":"4"},{"item":"35","conditions":"fzrcf","read_time":[5643],"image_error":false,"slider_value":98,"leftright_trial":"1left","list":"4"},{"item":"30","conditions":"fzrcf","read_time":[9520],"image_error":false,"slider_value":98,"leftright_trial":"1left","list":"4"},{"item":"17","conditions":"zrdf","read_time":[7306],"image_error":false,"slider_value":59,"leftright_trial":"1left","list":"4"},{"item":"1","conditions":"brdc","read_time":[7799],"image_error":false,"slider_value":50,"leftright_trial":"1right","list":"4"},{"item":"36","conditions":"fercf","read_time":[4347],"image_error":false,"slider_value":98,"leftright_trial":"1right","list":"4"},{"item":"19","conditions":"zrdf","read_time":[12368],"image_error":false,"slider_value":53,"leftright_trial":"1right","list":"4"},{"item":"16","conditions":"ercf","read_time":[7117],"image_error":false,"slider_value":2,"leftright_trial":"1left","list":"4"},{"item":"12","conditions":"brdc","read_time":[8910],"image_error":false,"slider_value":50,"leftright_trial":"1left","list":"4"},{"item":"31","conditions":"fbrcf","read_time":[4015],"image_error":false,"slider_value":98,"leftright_trial":"1right","list":"4"},{"item":"6","conditions":"brdf","read_time":[5176],"image_error":false,"slider_value":50,"leftright_trial":"1right","list":"4"},{"item":"32","conditions":"ferdf","read_time":[6913],"image_error":false,"slider_value":97,"leftright_trial":"1right","list":"4"},{"item":"10","conditions":"zrcf","read_time":[13587],"image_error":false,"slider_value":97,"leftright_trial":"1left","list":"4"},{"item":"27","conditions":"brcf","read_time":[4971],"image_error":false,"slider_value":50,"leftright_trial":"1left","list":"4"},{"item":"33","conditions":"ferdc","read_time":[4372],"image_error":false,"slider_value":2,"leftright_trial":"1left","list":"4"},{"item":"24","conditions":"brcf","read_time":[5854],"image_error":false,"slider_value":50,"leftright_trial":"1right","list":"4"},{"item":"32","conditions":"fzrdc","read_time":[24663],"image_error":false,"slider_value":75,"leftright_trial":"1left","list":"4"},{"item":"17","conditions":"erdf","read_time":[10864],"image_error":false,"slider_value":50,"leftright_trial":"1left","list":"4"},{"item":"20","conditions":"zrdc","read_time":[4584],"image_error":false,"slider_value":34,"leftright_trial":"1left","list":"4"},{"item":"31","conditions":"fbrdc","read_time":[7124],"image_error":false,"slider_value":98,"leftright_trial":"1right","list":"4"},{"item":"8","conditions":"zrcf","read_time":[6916],"image_error":false,"slider_value":27,"leftright_trial":"1left","list":"4"},{"item":"2","conditions":"zrcf","read_time":[9278],"image_error":false,"slider_value":21,"leftright_trial":"1right","list":"4"},{"item":"28","conditions":"ferdc","read_time":[8804],"image_error":false,"slider_value":76,"leftright_trial":"1left","list":"4"},{"item":"2","conditions":"brcf","read_time":[7956],"image_error":false,"slider_value":50,"leftright_trial":"1right","list":"4"},{"item":"11","conditions":"erdf","read_time":[7542],"image_error":false,"slider_value":2,"leftright_trial":"1left","list":"4"},{"item":"34","conditions":"fbrcf","read_time":[4065],"image_error":false,"slider_value":1,"leftright_trial":"1right","list":"4"},{"item":"29","conditions":"fbrdf","read_time":[4542],"image_error":false,"slider_value":98,"leftright_trial":"1right","list":"4"},{"item":"37","conditions":"fbrdf","read_time":[5260],"image_error":false,"slider_value":-1,"leftright_trial":"1left","list":"4"},{"item":"18","conditions":"erdc","read_time":[4910],"image_error":false,"slider_value":50,"leftright_trial":"1left","list":"4"},{"item":"23","conditions":"brdc","read_time":[16171],"image_error":false,"slider_value":71,"leftright_trial":"1right","list":"4"},{"item":"13","conditions":"ercf","read_time":[6211],"image_error":false,"slider_value":50,"leftright_trial":"1left","list":"4"},{"item":"36","conditions":"fbrdf","read_time":[5309],"image_error":false,"slider_value":-1,"leftright_trial":"1right","list":"4"},{"item":"34","conditions":"fzrcf","read_time":[10071],"image_error":false,"slider_value":97,"leftright_trial":"1left","list":"4"},{"item":"16","conditions":"brcf","read_time":[10508],"image_error":false,"slider_value":83,"leftright_trial":"1right","list":"4"},{"item":"17","conditions":"brdf","read_time":[5557],"image_error":false,"slider_value":50,"leftright_trial":"1right","list":"4"},{"item":"35","conditions":"ferdf","read_time":[6047],"image_error":false,"slider_value":96,"leftright_trial":"1right","list":"4"},{"item":"24","conditions":"zrcf","read_time":[9407],"image_error":false,"slider_value":50,"leftright_trial":"1left","list":"4"},{"item":"7","conditions":"erdc","read_time":[12014],"image_error":false,"slider_value":50,"leftright_trial":"1left","list":"4"},{"item":"23","conditions":"erdc","read_time":[4497],"image_error":false,"slider_value":2,"leftright_trial":"1left","list":"4"},{"item":"35","conditions":"fzrdf","read_time":[4047],"image_error":false,"slider_value":99,"leftright_trial":"1left","list":"4"},{"item":"38","conditions":"fbrcf","read_time":[5019],"image_error":false,"slider_value":-1,"leftright_trial":"1left","list":"4"},{"item":"28","conditions":"fzrcf","read_time":[8076],"image_error":false,"slider_value":41,"leftright_trial":"1right","list":"4"},{"item":"32","conditions":"fercf","read_time":[5921],"image_error":false,"slider_value":86,"leftright_trial":"1left","list":"4"},{"item":"3","conditions":"zrdf","read_time":[8275],"image_error":false,"slider_value":37,"leftright_trial":"1right","list":"4"},{"item":"29","conditions":"fbrcf","read_time":[5436],"image_error":false,"slider_value":3,"leftright_trial":"1left","list":"4"},{"item":"36","conditions":"fzrdc","read_time":[3946],"image_error":false,"slider_value":98,"leftright_trial":"1left","list":"4"},{"item":"32","conditions":"fbrcf","read_time":[6454],"image_error":false,"slider_value":99,"leftright_trial":"1right","list":"4"},{"item":"6","conditions":"zrdf","read_time":[4398],"image_error":false,"slider_value":50,"leftright_trial":"1right","list":"4"},{"item":"2","conditions":"ercf","read_time":[5691],"image_error":false,"slider_value":4,"leftright_trial":"1right","list":"4"},{"item":"14","conditions":"zrdf","read_time":[13142],"image_error":false,"slider_value":50,"leftright_trial":"1left","list":"4"},{"item":"25","conditions":"brdf","read_time":[9299],"image_error":false,"slider_value":91,"leftright_trial":"1right","list":"4"},{"item":"33","conditions":"fercf","read_time":[4075],"image_error":false,"slider_value":99,"leftright_trial":"1right","list":"4"},{"item":"22","conditions":"brdf","read_time":[5078],"image_error":false,"slider_value":50,"leftright_trial":"1left","list":"4"},{"item":"31","conditions":"ferdf","read_time":[5651],"image_error":false,"slider_value":98,"leftright_trial":"1right","list":"4"},{"item":"5","conditions":"zrcf","read_time":[5977],"image_error":false,"slider_value":50,"leftright_trial":"1left","list":"4"},{"item":"38","conditions":"fzrdf","read_time":[9514],"image_error":false,"slider_value":1,"leftright_trial":"1right","list":"4"},{"item":"15","conditions":"brdc","read_time":[4003],"image_error":false,"slider_value":50,"leftright_trial":"1left","list":"4"},{"item":"8","conditions":"brcf","read_time":[5570],"image_error":false,"slider_value":78,"leftright_trial":"1left","list":"4"},{"item":"30","conditions":"fbrcf","read_time":[3424],"image_error":false,"slider_value":98,"leftright_trial":"1right","list":"4"},{"item":"28","conditions":"fbrdc","read_time":[6637],"image_error":false,"slider_value":98,"leftright_trial":"1right","list":"4"},{"item":"38","conditions":"ferdf","read_time":[4144],"image_error":false,"slider_value":0,"leftright_trial":"1left","list":"4"},{"item":"33","conditions":"fzrcf","read_time":[5410],"image_error":false,"slider_value":28,"leftright_trial":"1right","list":"4"},{"item":"27","conditions":"zrcf","read_time":[5305],"image_error":false,"slider_value":50,"leftright_trial":"1left","list":"4"},{"item":"14","conditions":"brdf","read_time":[14299],"image_error":false,"slider_value":33,"leftright_trial":"1left","list":"4"},{"item":"29","conditions":"ferdc","read_time":[6747],"image_error":false,"slider_value":-1,"leftright_trial":"1right","list":"4"},{"item":"34","conditions":"fzrdc","read_time":[4712],"image_error":false,"slider_value":1,"leftright_trial":"1right","list":"4"},{"item":"25","conditions":"zrdf","read_time":[15152],"image_error":false,"slider_value":61,"leftright_trial":"1left","list":"4"},{"item":"7","conditions":"brdc","read_time":[5925],"image_error":false,"slider_value":75,"leftright_trial":"1right","list":"4"},{"item":"33","conditions":"fbrcf","read_time":[28784],"image_error":false,"slider_value":2,"leftright_trial":"1left","list":"4"},{"item":"35","conditions":"fbrcf","read_time":[4605],"image_error":false,"slider_value":-1,"leftright_trial":"1right","list":"4"},{"item":"26","conditions":"zrdc","read_time":[3744],"image_error":false,"slider_value":50,"leftright_trial":"1right","list":"4"},{"item":"11","conditions":"brdf","read_time":[4156],"image_error":false,"slider_value":50,"leftright_trial":"1left","list":"4"},{"item":"1","conditions":"zrdc","read_time":[4015],"image_error":false,"slider_value":14,"leftright_trial":"1right","list":"4"},{"item":"37","conditions":"fzrcf","read_time":[3421],"image_error":false,"slider_value":0,"leftright_trial":"1right","list":"4"},{"item":"31","conditions":"fzrdc","read_time":[4255],"image_error":false,"slider_value":21,"leftright_trial":"1right","list":"4"},{"item":"13","conditions":"zrcf","read_time":[5438],"image_error":false,"slider_value":14,"leftright_trial":"1right","list":"4"},{"item":"16","conditions":"zrcf","read_time":[13254],"image_error":false,"slider_value":90,"leftright_trial":"1left","list":"4"},{"item":"36","conditions":"fzrcf","read_time":[3673],"image_error":false,"slider_value":98,"leftright_trial":"1left","list":"4"},{"item":"8","conditions":"ercf","read_time":[5091],"image_error":false,"slider_value":95,"leftright_trial":"1right","list":"4"},{"item":"32","conditions":"fzrcf","read_time":[5697],"image_error":false,"slider_value":18,"leftright_trial":"1right","list":"4"},{"item":"24","conditions":"ercf","read_time":[4198],"image_error":false,"slider_value":87,"leftright_trial":"1right","list":"4"},{"item":"18","conditions":"zrdc","read_time":[5710],"image_error":false,"slider_value":85,"leftright_trial":"1left","list":"4"},{"item":"35","conditions":"ferdc","read_time":[5602],"image_error":false,"slider_value":2,"leftright_trial":"1left","list":"4"},{"item":"36","conditions":"fbrdc","read_time":[4167],"image_error":false,"slider_value":99,"leftright_trial":"1left","list":"4"},{"item":"31","conditions":"ferdc","read_time":[11142],"image_error":false,"slider_value":2,"leftright_trial":"1left","list":"4"},{"item":"34","conditions":"fercf","read_time":[3581],"image_error":false,"slider_value":98,"leftright_trial":"1right","list":"4"},{"item":"37","conditions":"fzrdf","read_time":[6742],"image_error":false,"slider_value":1,"leftright_trial":"1right","list":"4"},{"item":"4","conditions":"zrdc","read_time":[4921],"image_error":false,"slider_value":76,"leftright_trial":"1left","list":"4"},{"item":"38","conditions":"fzrcf","read_time":[5428],"image_error":false,"slider_value":-1,"leftright_trial":"1left","list":"4"},{"item":"12","conditions":"erdc","read_time":[6849],"image_error":false,"slider_value":81,"leftright_trial":"1right","list":"4"},{"item":"31","conditions":"fercf","read_time":[4142],"image_error":false,"slider_value":98,"leftright_trial":"1right","list":"4"},{"item":"36","conditions":"fzrdf","read_time":[3472],"image_error":false,"slider_value":98,"leftright_trial":"1left","list":"4"},{"item":"1","conditions":"erdc","read_time":[8127],"image_error":false,"slider_value":67,"leftright_trial":"1right","list":"4"},{"item":"18","conditions":"brdc","read_time":[6729],"image_error":false,"slider_value":15,"leftright_trial":"1right","list":"4"},{"item":"27","conditions":"ercf","read_time":[14682],"image_error":false,"slider_value":70,"leftright_trial":"1right","list":"4"},{"item":"38","conditions":"fercf","read_time":[3843],"image_error":false,"slider_value":99,"leftright_trial":"1right","list":"4"},{"item":"11","conditions":"zrdf","read_time":[4562],"image_error":false,"slider_value":81,"leftright_trial":"1left","list":"4"},{"item":"9","conditions":"erdf","read_time":[8891],"image_error":false,"slider_value":-1,"leftright_trial":"1right","list":"4"},{"item":"35","conditions":"fzrdc","read_time":[3539],"image_error":false,"slider_value":0,"leftright_trial":"1right","list":"4"},{"item":"10","conditions":"ercf","read_time":[4146],"image_error":false,"slider_value":13,"leftright_trial":"1left","list":"4"},{"item":"19","conditions":"erdf","read_time":[6172],"image_error":false,"slider_value":11,"leftright_trial":"1left","list":"4"},{"item":"37","conditions":"fbrcf","read_time":[6836],"image_error":false,"slider_value":-1,"leftright_trial":"1right","list":"4"},{"item":"5","conditions":"ercf","read_time":[7175],"image_error":false,"slider_value":81,"leftright_trial":"1right","list":"4"},{"item":"9","conditions":"zrdf","read_time":[10333],"image_error":false,"slider_value":87,"leftright_trial":"1left","list":"4"},{"item":"33","conditions":"fzrdf","read_time":[5253],"image_error":false,"slider_value":87,"leftright_trial":"1left","list":"4"},{"item":"36","conditions":"fbrcf","read_time":[7016],"image_error":false,"slider_value":-1,"leftright_trial":"1left","list":"4"},{"item":"30","conditions":"fbrdf","read_time":[3655],"image_error":false,"slider_value":98,"leftright_trial":"1right","list":"4"},{"item":"21","conditions":"zrcf","read_time":[11560],"image_error":false,"slider_value":90,"leftright_trial":"1left","list":"4"},{"item":"13","conditions":"brcf","read_time":[9907],"image_error":false,"slider_value":11,"leftright_trial":"1right","list":"4"},{"item":"33","conditions":"fbrdc","read_time":[6010],"image_error":false,"slider_value":98,"leftright_trial":"1right","list":"4"},{"item":"30","conditions":"ferdc","read_time":[5898],"image_error":false,"slider_value":-1,"leftright_trial":"1right","list":"4"},{"item":"28","conditions":"ferdf","read_time":[9670],"image_error":false,"slider_value":84,"leftright_trial":"1left","list":"4"},{"item":"23","conditions":"zrdc","read_time":[6530],"image_error":false,"slider_value":92,"leftright_trial":"1left","list":"4"},{"item":"34","conditions":"fbrdc","read_time":[4240],"image_error":false,"slider_value":-1,"leftright_trial":"1left","list":"4"},{"item":"35","conditions":"fbrdc","read_time":[5232],"image_error":false,"slider_value":-1,"leftright_trial":"1right","list":"4"},{"item":"29","conditions":"fbrdc","read_time":[4602],"image_error":false,"slider_value":98,"leftright_trial":"1right","list":"4"},{"item":"5","conditions":"brcf","read_time":[8192],"image_error":false,"slider_value":50,"leftright_trial":"1left","list":"4"},{"item":"26","conditions":"erdc","read_time":[6286],"image_error":false,"slider_value":9,"leftright_trial":"1left","list":"4"},{"item":"31","conditions":"fzrdf","read_time":[7921],"image_error":false,"slider_value":10,"leftright_trial":"1right","list":"4"},{"item":"15","conditions":"zrdc","read_time":[7212],"image_error":false,"slider_value":50,"leftright_trial":"1right","list":"4"},{"item":"30","conditions":"ferdf","read_time":[6983],"image_error":false,"slider_value":87,"leftright_trial":"1left","list":"4"},{"item":"33","conditions":"ferdf","read_time":[4598],"image_error":false,"slider_value":0,"leftright_trial":"1left","list":"4"},{"item":"3","conditions":"erdf","read_time":[7179],"image_error":false,"slider_value":32,"leftright_trial":"1left","list":"4"},{"item":"6","conditions":"erdf","read_time":[4898],"image_error":false,"slider_value":22,"leftright_trial":"1left","list":"4"},{"item":"30","conditions":"fercf","read_time":[4628],"image_error":false,"slider_value":17,"leftright_trial":"1right","list":"4"},{"item":"28","conditions":"fbrdf","read_time":[4159],"image_error":false,"slider_value":1,"leftright_trial":"1left","list":"4"},{"item":"10","conditions":"brcf","read_time":[11047],"image_error":false,"slider_value":50,"leftright_trial":"1left","list":"4"},{"item":"32","conditions":"ferdc","read_time":[9673],"image_error":false,"slider_value":2,"leftright_trial":"1left","list":"4"},{"item":"35","conditions":"fbrdf","read_time":[8507],"image_error":false,"slider_value":-1,"leftright_trial":"1right","list":"4"},{"item":"3","conditions":"brdf","read_time":[4929],"image_error":false,"slider_value":50,"leftright_trial":"1left","list":"4"},{"item":"37","conditions":"ferdf","read_time":[3894],"image_error":false,"slider_value":99,"leftright_trial":"1right","list":"4"},{"item":"31","conditions":"fzrcf","read_time":[4792],"image_error":false,"slider_value":18,"leftright_trial":"1right","list":"4"},{"item":"35","conditions":"fercf","read_time":[3780],"image_error":false,"slider_value":98,"leftright_trial":"1right","list":"4"},{"item":"19","conditions":"brdf","read_time":[13838],"image_error":false,"slider_value":21,"leftright_trial":"1left","list":"4"},{"item":"29","conditions":"fzrcf","read_time":[4104],"image_error":false,"slider_value":7,"leftright_trial":"1right","list":"4"},{"item":"38","conditions":"fzrdc","read_time":[4581],"image_error":false,"slider_value":99,"leftright_trial":"1left","list":"4"},{"item":"33","conditions":"fbrdf","read_time":[4954],"image_error":false,"slider_value":1,"leftright_trial":"1left","list":"4"},{"item":"37","conditions":"fzrdc","read_time":[3228],"image_error":false,"slider_value":1,"leftright_trial":"1right","list":"4"},{"item":"20","conditions":"erdc","read_time":[7836],"image_error":false,"slider_value":81,"leftright_trial":"1right","list":"4"},{"item":"36","conditions":"ferdc","read_time":[5052],"image_error":false,"slider_value":98,"leftright_trial":"1right","list":"4"},{"item":"22","conditions":"zrdf","read_time":[6368],"image_error":false,"slider_value":11,"leftright_trial":"1right","list":"4"},{"item":"20","conditions":"brdc","read_time":[7606],"image_error":false,"slider_value":89,"leftright_trial":"1right","list":"4"},{"item":"34","conditions":"ferdc","read_time":[4953],"image_error":false,"slider_value":99,"leftright_trial":"1right","list":"4"},{"item":"7","conditions":"zrdc","read_time":[11577],"image_error":false,"slider_value":17,"leftright_trial":"1right","list":"4"},{"item":"9","conditions":"brdf","read_time":[6732],"image_error":false,"slider_value":89,"leftright_trial":"1right","list":"4"},{"item":"21","conditions":"brcf","read_time":[7984],"image_error":false,"slider_value":72,"leftright_trial":"1left","list":"4"}],"id":"6240858c0e147c","catch_trials":[],"block_boundaries":[53,90,143],"system":{"Browser":"Chrome","OS":"Mac","screenH":900,"screenW":1440},"condition":"S","subject_information":{"language":"deutsch","asses":"Yes","age":"21","gender":"Female","comments":"","fluent":"Yes"},"time_in_minutes":25.526216666666667,"missed_break_one":false,"missed_break_two":false,"missed_break_three":false}